fb4/__init__.py
fb4/ekz_data.py
fb4/poisk.py
fb4-1.0.11.dist-info/LICENSE.txt
fb4-1.0.11.dist-info/METADATA
fb4-1.0.11.dist-info/WHEEL
fb4-1.0.11.dist-info/top_level.txt
fb4-1.0.11.dist-info/RECORD
