Metadata-Version: 2.1
Name: fb4
Version: 1.0.11
Summary: xD
Author: qdzzzxc
Keywords: example python
Classifier: Programming Language :: Python :: 3.7
Classifier: License :: OSI Approved :: MIT License
Classifier: Operating System :: OS Independent
Requires-Python: >=3.7
License-File: LICENSE.txt
Requires-Dist: pyperclip (>=1.8.2)
Requires-Dist: fuzzywuzzy (>=0.18.0)
